tape/__init__.py
tape/datasets.py
tape/errors.py
tape/main.py
tape/metrics.py
tape/optimization.py
tape/registry.py
tape/tokenizers.py
tape/training.py
tape/visualization.py
tape/models/__init__.py
tape/models/file_utils.py
tape/models/modeling_bert.py
tape/models/modeling_lstm.py
tape/models/modeling_onehot.py
tape/models/modeling_resnet.py
tape/models/modeling_trrosetta.py
tape/models/modeling_unirep.py
tape/models/modeling_utils.py
tape/utils/__init__.py
tape/utils/_sampler.py
tape/utils/distributed_utils.py
tape/utils/setup_utils.py
tape/utils/utils.py
tape_proteins-0.5.dist-info/LICENSE
tape_proteins-0.5.dist-info/METADATA
tape_proteins-0.5.dist-info/WHEEL
tape_proteins-0.5.dist-info/entry_points.txt
tape_proteins-0.5.dist-info/top_level.txt
tape_proteins-0.5.dist-info/RECORD
