Metadata-Version: 2.1
Name: tape-proteins
Version: 0.5
Summary: Repostory of Protein Benchmarking and Modeling
Home-page: https://github.com/songlab-cal/tape
Author: Roshan Rao, Nick Bhattacharya, Neil Thomas
Author-email: roshan_rao@berkeley.edu, nickbhat@berkeley.edu, nthomas@berkeley.edu
License: BSD 3-Clause License
Requires-Dist: tqdm
Requires-Dist: tensorboardX
Requires-Dist: scipy
Requires-Dist: lmdb
Requires-Dist: boto3
Requires-Dist: requests
Requires-Dist: biopython
Requires-Dist: filelock
